odoo/addons/stock_partner_delivery_window/README.rst
odoo/addons/stock_partner_delivery_window/__init__.py
odoo/addons/stock_partner_delivery_window/__manifest__.py
odoo/addons/stock_partner_delivery_window/demo/delivery_time_window.xml
odoo/addons/stock_partner_delivery_window/i18n/stock_partner_delivery_window.pot
odoo/addons/stock_partner_delivery_window/models/__init__.py
odoo/addons/stock_partner_delivery_window/models/delivery_time_window.py
odoo/addons/stock_partner_delivery_window/models/res_partner.py
odoo/addons/stock_partner_delivery_window/models/stock_picking.py
odoo/addons/stock_partner_delivery_window/readme/CONFIGURE.rst
odoo/addons/stock_partner_delivery_window/readme/CONTRIBUTORS.rst
odoo/addons/stock_partner_delivery_window/readme/DESCRIPTION.rst
odoo/addons/stock_partner_delivery_window/security/ir.model.access.csv
odoo/addons/stock_partner_delivery_window/static/description/icon.png
odoo/addons/stock_partner_delivery_window/static/description/index.html
odoo/addons/stock_partner_delivery_window/tests/__init__.py
odoo/addons/stock_partner_delivery_window/tests/test_delivery_window.py
odoo/addons/stock_partner_delivery_window/views/res_partner.xml
odoo13_addon_stock_partner_delivery_window-13.0.1.3.2.dist-info/METADATA
odoo13_addon_stock_partner_delivery_window-13.0.1.3.2.dist-info/WHEEL
odoo13_addon_stock_partner_delivery_window-13.0.1.3.2.dist-info/top_level.txt
odoo13_addon_stock_partner_delivery_window-13.0.1.3.2.dist-info/RECORD
