Metadata-Version: 2.1
Name: odoo13-addon-stock-partner-delivery-window
Version: 13.0.1.3.2
Summary: Define preferred delivery time windows for partners
Home-page: https://github.com/OCA/stock-logistics-workflow
Author: Camptocamp, ACSONE SA/NV, Odoo Community Association (OCA)
Author-email: support@odoo-community.org
License: AGPL-3
Platform: UNKNOWN
Classifier: Programming Language :: Python
Classifier: Framework :: Odoo
Classifier: Framework :: Odoo :: 13.0
Classifier: License :: OSI Approved :: GNU Affero General Public License v3
Classifier: Development Status :: 3 - Alpha
Requires-Python: >=3.5
Requires-Dist: odoo13-addon-base-time-window
Requires-Dist: odoo13-addon-partner-tz
Requires-Dist: odoo (<13.1dev,>=13.0a)
